pandacite/__init__.py
pandacite/citation_manager.py
pandacite/cli.py
pandacite/complete_citation_manager_bakup.py
pandacite/extractors/__init__.py
pandacite/extractors/detector.py
pandacite/extractors/metadata.py
pandacite/formatters/__init__.py
pandacite/formatters/base.py
pandacite/formatters/basic.py
pandacite/formatters/scientific.py
pandacite/parsers/__init__.py
pandacite/parsers/arxiv.py
pandacite/parsers/doi.py
pandacite/parsers/others.py
pandacite/parsers/pmid.py
pandacite/processors/__init__.py
pandacite/processors/numbered.py
pandacite/processors/word.py
pandacite-0.3.0.dist-info/licenses/LICENSE
pandacite-0.3.0.dist-info/METADATA
pandacite-0.3.0.dist-info/WHEEL
pandacite-0.3.0.dist-info/entry_points.txt
pandacite-0.3.0.dist-info/top_level.txt
pandacite-0.3.0.dist-info/RECORD
