Metadata-Version: 2.4
Name: pandacite
Version: 0.3.0
Summary: A Python-based citation manager
Author-email: "Dr. Pritam Kumar Panda" <pritam@stanford.edu>
License: MIT
Project-URL: Homepage, https://github.com/pritampanda15/pandacite
Project-URL: Issues, https://github.com/pritampanda15/pandacite/issues
Keywords: citation,manager,docx,reference,mendeley,endnote
Classifier: Programming Language :: Python :: 3
Classifier: License :: OSI Approved :: MIT License
Classifier: Operating System :: OS Independent
Requires-Python: >=3.6
License-File: LICENSE
Requires-Dist: aiohappyeyeballs==2.6.1
Requires-Dist: aiohttp==3.11.18
Requires-Dist: aiosignal==1.3.2
Requires-Dist: asyncio==3.4.3
Requires-Dist: attrs==25.3.0
Requires-Dist: beautifulsoup4==4.13.4
Requires-Dist: build==1.2.2.post1
Requires-Dist: certifi==2025.4.26
Requires-Dist: charset-normalizer==3.4.2
Requires-Dist: colorama==0.4.6
Requires-Dist: disutils==1.4.32.post2
Requires-Dist: docutils==0.21.2
Requires-Dist: frozenlist==1.6.0
Requires-Dist: id==1.5.0
Requires-Dist: idna==3.10
Requires-Dist: jaraco.classes==3.4.0
Requires-Dist: jaraco.context==6.0.1
Requires-Dist: jaraco.functools==4.1.0
Requires-Dist: keyring==25.6.0
Requires-Dist: lxml==5.4.0
Requires-Dist: markdown-it-py==3.0.0
Requires-Dist: mdurl==0.1.2
Requires-Dist: more-itertools==10.7.0
Requires-Dist: multidict==6.4.3
Requires-Dist: nh3==0.2.21
Requires-Dist: packaging==25.0
Requires-Dist: prompt_toolkit==3.0.51
Requires-Dist: propcache==0.3.1
Requires-Dist: Pygments==2.19.1
Requires-Dist: pyproject_hooks==1.2.0
Requires-Dist: python-docx==1.1.2
Requires-Dist: readme_renderer==44.0
Requires-Dist: requests==2.32.3
Requires-Dist: requests-toolbelt==1.0.0
Requires-Dist: rfc3986==2.0.0
Requires-Dist: rich==14.0.0
Requires-Dist: setuptools==80.3.1
Requires-Dist: soupsieve==2.7
Requires-Dist: twine==6.1.0
Requires-Dist: typing_extensions==4.13.2
Requires-Dist: urllib3==2.4.0
Requires-Dist: wcwidth==0.2.13
Requires-Dist: yarl==1.20.0
Provides-Extra: dev
Requires-Dist: pytest; extra == "dev"
Requires-Dist: flake8; extra == "dev"
Requires-Dist: black; extra == "dev"
Dynamic: license-file
